IntegralElimination/IntegralAlgebra.py
IntegralElimination/IntegralMonomial.py
IntegralElimination/IntegralPolynomial.py
IntegralElimination/__init__.py
IntegralElimination/convert.py
IntegralElimination/critical_pairs.py
IntegralElimination/exponentials.py
IntegralElimination/integral_elimination.py
IntegralElimination/ordering.py
IntegralElimination/reduction.py
IntegralElimination/utils.py
IntegralElimination-1.0.dist-info/LICENSE
IntegralElimination-1.0.dist-info/METADATA
IntegralElimination-1.0.dist-info/WHEEL
IntegralElimination-1.0.dist-info/top_level.txt
IntegralElimination-1.0.dist-info/RECORD
