Metadata-Version: 2.1
Name: IntegralElimination
Version: 1.0
Summary: Algorithm for performing integral elimination for nonlinear integral equations
Home-page: https://codeberg.org/louis-roussel/IntegralElimination
Author: Louis ROUSSEL
Author-email: louis.roussel@univ-lille.fr
Requires-Python: >=3.9
License-File: LICENSE
Requires-Dist: ordered-set (>=4.1.0)
Requires-Dist: sympy (>=1.11.1)
Requires-Dist: typing (>=3.7.4.3)
Requires-Dist: numpy
